odoo/addons/survey_result_mail/README.rst
odoo/addons/survey_result_mail/__init__.py
odoo/addons/survey_result_mail/__manifest__.py
odoo/addons/survey_result_mail/data/mail_template.xml
odoo/addons/survey_result_mail/i18n/es.po
odoo/addons/survey_result_mail/i18n/it.po
odoo/addons/survey_result_mail/i18n/survey_result_mail.pot
odoo/addons/survey_result_mail/migrations/17.0.1.0.0/noupdate_changes.xml
odoo/addons/survey_result_mail/migrations/17.0.1.0.0/post-migration.py
odoo/addons/survey_result_mail/models/__init__.py
odoo/addons/survey_result_mail/models/survey_survey.py
odoo/addons/survey_result_mail/models/survey_user_input.py
odoo/addons/survey_result_mail/readme/CONFIGURE.md
odoo/addons/survey_result_mail/readme/CONTRIBUTORS.md
odoo/addons/survey_result_mail/readme/DESCRIPTION.md
odoo/addons/survey_result_mail/readme/USAGE.md
odoo/addons/survey_result_mail/reports/survey_answer_report.xml
odoo/addons/survey_result_mail/static/description/icon.png
odoo/addons/survey_result_mail/static/description/index.html
odoo/addons/survey_result_mail/templates/survey_answer_templates.xml
odoo/addons/survey_result_mail/tests/__init__.py
odoo/addons/survey_result_mail/tests/test_survey_result_mail.py
odoo/addons/survey_result_mail/views/survey_survey_views.xml
odoo/addons/survey_result_mail/views/survey_user_input_views.xml
odoo_addon_survey_result_mail-17.0.1.0.0.2.dist-info/METADATA
odoo_addon_survey_result_mail-17.0.1.0.0.2.dist-info/WHEEL
odoo_addon_survey_result_mail-17.0.1.0.0.2.dist-info/top_level.txt
odoo_addon_survey_result_mail-17.0.1.0.0.2.dist-info/RECORD
